aioxrocket/__init__.py
aioxrocket-0.0.0.dist-info/METADATA
aioxrocket-0.0.0.dist-info/WHEEL
aioxrocket-0.0.0.dist-info/top_level.txt
aioxrocket-0.0.0.dist-info/RECORD
