Metadata-Version: 2.4
Name: aioxrocket
Version: 0.0.0
Summary: 🚀 xRocket client
Requires-Python: >=3.13
